gigaHurt/components/clock/clock.sv
//////////////////////////////////////////////////////////////////////////////////
// The Cooper Union
// ECE 251 Spring 2023
// Engineer: Lizelle Ocfemia & Nicholas Storniolo
// 
//     Create Date: 2023-05-01
//     Module Name: clock
//     Description: Clock generator; duty cycle = 50%
//
// Revision: 1.0
//
//////////////////////////////////////////////////////////////////////////////////
`ifndef CLOCK
`define CLOCK

`timescale 1ns/100ps

module clock
    #(parameter ticks = 10)(
    //
    // ---------------- PORT DEFINITIONS ----------------
    //
    input ENABLE,
    output reg CLOCK
);
    //
    // ---------------- MODULE DESIGN IMPLEMENTATION ----------------
    //
    reg start_clock;
    real clock_on = ticks/2; // duty cycle = 50%
    real clock_off = ticks/2;

    // initialize variables
    initial begin
      CLOCK <= 0;
      start_clock <= 0;
    end

    always @(posedge ENABLE or negedge ENABLE) begin
        if (ENABLE) begin
            start_clock = 1;
        end
        else begin
            start_clock = 0;
        end
        // #ticks CLOCK = ~CLOCK;
    end
    always @(start_clock) begin
        CLOCK = 0;
        while (start_clock) begin
            #(clock_off) CLOCK = 1;
            #(clock_on) CLOCK = 0;
        end
        CLOCK = 0;
    end
endmodule

`endif // CLOCK

gigaHurt/components/alu/alu.sv
//////////////////////////////////////////////////////////////////////////////////
// The Cooper Union
// ECE 251 Spring 2023
// Engineer: gigaHurt
// 
//     Create Date: 2023-02-07
//     Module Name: alu
//     Description: arithmetic logic unit
//
// Revision: 1.0
//
//////////////////////////////////////////////////////////////////////////////////
`ifndef ALU
`define ALU

`timescale 1ns/100ps

module alu
    #(parameter n = 16)(
    input  logic clk,
    input  logic [(n-1):0] a, b,
    input  logic [3:0]  alucontrol,
    output logic [(n-1):0] result,
    output logic zero
);
    logic [(n-1):0] condinvb, sum;
    logic [(2*n-1):0] HiLo;

    assign zero = (result == {n{1'b0}}); // zero result control signal
    assign condinvb = alucontrol[3] ? ~b : b;
    assign sumSlt = a + condinvb + alucontrol[3]; // (a-b using 2s complement) test if a == b, if b<a, then sumSlt will have neg bit[31]

    // init HiLo register (n bit num * n bit num = 2n bit num)
    // initial
    //     begin
    //         HiLo = (2*n)'b0;
    //     end

    always @(a,b,alucontrol) begin
        case (alucontrol)
            4'b0000: result = a & b;             // and
            4'b0001: result = a | b;             // or
            4'b0010: result = ~(a | b);          // nor
            4'b0011: result = a + b;             // add
            4'b0100: result = sumSlt;            // sub
            4'b1001: result = sumSlt[(n-1)];      // slt

            // 3'b111: result = sumSlt[(n-1)];     // slt
            
            // 3'b000: result = a & b;             // and
            // 3'b001: result = a | b;             // or
            // 3'b010: result = a + b;             // add
            // 3'b011: result = ~(a | b);           // nor
            // 3'b100: result = HiLo[(n-1):0];     // MFLO
            // 3'b101: result = HiLo[(2*n-1):n];   // MFHI
            // 3'b110: result = sumSlt;            // sub
            // // 3'b111: result = sumSlt[(n-1)];     // slt
            
            4'b1001: begin                       // slt
				if (a[n-1] != b[n-1])
					if (a[n-1] > b[n-1])
						result = 1;
					else
						result = 0;
				else
					if (a < b)
						result = 1;
					else
						result = 0;
            end
        endcase
    end

    //Multiply and divide results are only stored at clock falling edge.
    // always @(negedge clk) begin
    //     case (alucontrol)
    //         4'b0101: HiLo = a * b; // mult
    //         4'b1000: // div
    //         begin
    //             HiLo[(n-1):0] = a / b;
    //             HiLo[(2*n-1):n] = a % b;
    //         end
    //     endcase				
    // end

endmodule

`endif

gigaHurt/components/alu/alu_tb.sv
//////////////////////////////////////////////////////////////////////////////////
// The Cooper Union
// ECE 251 Spring 2023
// Engineer: gigaHurt
// 
//     Create Date: 2023-02-07
//     Module Name: alu_tb
//     Description: arithmetic logic unit testbench
//
// Revision: 1.0
//
//////////////////////////////////////////////////////////////////////////////////
`ifndef TB_ALU
`define TB_ALU

`timescale 1ns/100ps
`include "alu.sv"
`include "../clock/clock.sv"

module alu_tb;
    parameter n = 16;
    wire clk;
    logic clock_enable;
    logic [(n-1):0] A, B;
    logic [3:0] aluctrl;
    logic [(n-1):0] Y;
    integer i;

   initial begin
        $dumpfile("alu.vcd");
        $dumpvars(0, uut, uut1);
        $monitor("time=%0t alu_ctrl=%b A=%b B=%b Y=%b",
                 $realtime, aluctrl, A, B, Y);
    end

    initial begin
        #10 clock_enable <= 1;
        A <= #n'h00F;
        B <= #n'h0F1;
        aluctrl <= 4'b0000;
        #20
        
        for (i=0; i<5; i = i+1)
        begin
            A <= #n'h00F;
            B <= #n'h0F1;
            aluctrl = aluctrl + 4'b0001;
            #10;
        end
            
            A <= #n'h00F;
            B <= #n'h0F1;
            aluctrl = 4'b1000;
            #10;

            A <= #n'h00F;
            B <= #n'h0F1;
            aluctrl = 4'b1001;
            #10;


        $finish;
    end
    
   alu uut(
        .clk(clk),
        .a(A),
        .b(B),
        .alucontrol(aluctrl),
        .result(Y)
    );

    clock uut1(
        .ENABLE(clock_enable),
        .CLOCK(clk)
    );
endmodule

`endif // TB_ALU

gigaHurt/components/alu/alu.vcd
$date
	Tue May  9 18:49:42 2023
$end
$version
	Icarus Verilog
$end
$timescale
	100ps
$end
$scope module alu_tb $end
$scope module uut $end
$var wire 16 ! a [15:0] $end
$var wire 4 " alucontrol [3:0] $end
$var wire 16 # b [15:0] $end
$var wire 1 $ zero $end
$var wire 16 % sumSlt [15:0] $end
$var wire 16 & condinvb [15:0] $end
$var wire 1 ' clk $end
$var reg 32 ( HiLo [31:0] $end
$var reg 16 ) result [15:0] $end
$upscope $end
$upscope $end
$scope module alu_tb $end
$scope module uut1 $end
$var wire 1 * ENABLE $end
$var reg 1 ' CLOCK $end
$var reg 1 + start_clock $end
$var real 1 , clock_off $end
$var real 1 - clock_on $end
$upscope $end
$upscope $end
$enddefinitions $end
#0
$dumpvars
r5 -
r5 ,
0+
x*
bx )
b0 (
0'
bx &
bx %
x$
bx #
bx "
bx !
$end
#100
1+
b0 "
1*
#150
1'
#200
0'
#250
1'
#260
b100000000 %
b11110001 &
0$
b1 )
b11110001 #
b1111 !
#300
b11111111 )
0'
b1 "
#350
1'
#400
b1111111100000000 )
0'
b10 "
#450
1'
#500
b100000000 )
0'
b11 "
#550
1'
#600
b1111111100001110 &
b100000001 )
b1111111100011110 %
0'
b100 "
#650
1'
#700
b111000011111 (
0'
b101 "
#750
1'
#800
b11110001 &
b11110000000000000000 (
b100000000 %
0'
b1000 "
#850
1'
#900
1$
b0 )
0'
b1001 "
