gigaHurt/components/clock/clock.sv
//////////////////////////////////////////////////////////////////////////////////
// The Cooper Union
// ECE 251 Spring 2023
// Engineer: Lizelle Ocfemia & Nicholas Storniolo
// 
//     Create Date: 2023-05-01
//     Module Name: clock
//     Description: Clock generator; duty cycle = 50%
//
// Revision: 1.0
//
//////////////////////////////////////////////////////////////////////////////////
`ifndef CLOCK
`define CLOCK

`timescale 1ns/100ps

module clock
    #(parameter ticks = 10)(
    //
    // ---------------- PORT DEFINITIONS ----------------
    //
    input ENABLE,
    output reg CLOCK
);
    //
    // ---------------- MODULE DESIGN IMPLEMENTATION ----------------
    //
    reg start_clock;
    real clock_on = ticks/2; // duty cycle = 50%
    real clock_off = ticks/2;

    // initialize variables
    initial begin
      CLOCK <= 0;
      start_clock <= 0;
    end

    always @(posedge ENABLE or negedge ENABLE) begin
        if (ENABLE) begin
            start_clock = 1;
        end
        else begin
            start_clock = 0;
        end
        // #ticks CLOCK = ~CLOCK;
    end
    always @(start_clock) begin
        CLOCK = 0;
        while (start_clock) begin
            #(clock_off) CLOCK = 1;
            #(clock_on) CLOCK = 0;
        end
        CLOCK = 0;
    end
endmodule

`endif // CLOCK

gigaHurt/components/dmem/dmem.sv
//////////////////////////////////////////////////////////////////////////////////
// The Cooper Union
// ECE 251 Spring 2023
// Engineer: gigaHurt
// 
//     Create Date: 2023-02-07
//     Module Name: dmem
//     Description: data memory
//
// Revision: 1.0
//
//////////////////////////////////////////////////////////////////////////////////
`ifndef DMEM
`define DMEM

`timescale 1ns/100ps

module dmem
    #(parameter n = 16, parameter r = 5)(

    input  logic clk, write_enable,
    input  logic [(n-1):0] addr, writedata,
    output logic [(n-1):0] readdata
);
    logic [(n-1):0] RAM[0:((2**r)-1)];

    assign readdata = RAM[addr[(n-1):2]]; // word aligned (ignores lower 2 bits of address)

    always @(posedge clk)
        if (write_enable) RAM[addr[(n-1):2]] <= writedata;

endmodule

`endif

gigaHurt/components/dmem/dmem_tb.sv
//////////////////////////////////////////////////////////////////////////////////
// The Cooper Union
// ECE 251 Spring 2023
// Engineer: Prof Rob Marano
// 
//     Create Date: 2023-02-07
//     Module Name: tb_dmem
//     Description: Test bench for data memory
//
// Revision: 1.0
//
//////////////////////////////////////////////////////////////////////////////////
`ifndef TB_DMEM
`define TB_DMEM

`timescale 1ns/100ps
`include "dmem.sv"
`include "../clock/clock.sv"

module tb_dmem;
    parameter n = 16; // bit length of registers/memory
    parameter r = 5; // we are only addressing 64=2**6 mem slots in imem
    logic [(n-1):0] readdata, writedata;
    logic [(n-1):0] dmem_addr;
    logic write_enable;
    logic clk, clock_enable;

   initial begin
        $dumpfile("dmem.vcd");
        $dumpvars(0, uut, uut1);
        $monitor("time=%0t write_enable=%b dmem_addr=%h readdata=%h writedata=%h",
            $realtime, write_enable, dmem_addr, readdata, writedata);
    end

    initial begin
        #10 clock_enable <= 1;
        #20 writedata = #(n)'hFFFF;
        #20 dmem_addr <= #(r)'b00000;
        #20 write_enable <= 1;
        #20 write_enable <= 0;
        #20 dmem_addr <= #(r)'b00001;
        #20 writedata = #(n)'h00FF;
        #20 write_enable <= 1;
        #20 write_enable <= 0;
        #20 dmem_addr <= #(r)'b00010;
        #20 writedata = #(n)'h0000;
        #20 write_enable <= 1;
        #20 write_enable <= 0;
        #20 $finish;
    end

   dmem uut(
        .clk(clk),
        .write_enable(write_enable),
        .addr(dmem_addr),
        .writedata(writedata),
        .readdata(readdata)
    );
    clock uut1(
        .ENABLE(clock_enable),
        .CLOCK(clk)
    );
endmodule

`endif // TB_IMEM

gigaHurt/components/dmem/dmem.vcd
$date
	Tue May  9 12:38:46 2023
$end
$version
	Icarus Verilog
$end
$timescale
	100ps
$end
$scope module tb_dmem $end
$scope module uut $end
$var wire 16 ! addr [15:0] $end
$var wire 16 " readdata [15:0] $end
$var wire 1 # write_enable $end
$var wire 16 $ writedata [15:0] $end
$var wire 1 % clk $end
$upscope $end
$upscope $end
$scope module tb_dmem $end
$scope module uut1 $end
$var wire 1 & ENABLE $end
$var reg 1 % CLOCK $end
$var reg 1 ' start_clock $end
$var real 1 ( clock_off $end
$var real 1 ) clock_on $end
$upscope $end
$upscope $end
$enddefinitions $end
#0
$dumpvars
r5 )
r5 (
0'
x&
0%
bx $
x#
bx "
bx !
$end
#100
1'
1&
#150
1%
#200
0%
#250
1%
#300
0%
#350
1%
#400
0%
#450
1%
#460
b1111111111111111 $
#500
0%
#550
1%
#600
0%
#650
1%
#700
0%
#710
b0 !
#750
1%
#800
0%
#850
1%
#860
1#
#900
0%
#950
b1111111111111111 "
1%
#1000
0%
#1050
1%
#1060
0#
#1100
0%
#1150
1%
#1200
0%
#1250
1%
#1300
0%
#1310
b1 !
#1350
1%
#1400
0%
#1450
1%
#1500
0%
#1550
1%
#1600
0%
#1620
b11111111 $
#1650
1%
#1700
0%
#1750
1%
#1800
0%
#1820
1#
#1850
b11111111 "
1%
#1900
0%
#1950
1%
#2000
0%
#2020
0#
#2050
1%
#2100
0%
#2150
1%
#2200
0%
#2250
1%
#2270
b10 !
#2300
0%
#2350
1%
#2400
0%
#2450
1%
#2500
0%
#2550
1%
#2580
b0 $
#2600
0%
#2650
1%
#2700
0%
#2750
1%
#2780
1#
#2800
0%
#2850
b0 "
1%
#2900
0%
#2950
1%
#2980
0#
