gigaHurt/components/clock/clock.sv
//////////////////////////////////////////////////////////////////////////////////
// The Cooper Union
// ECE 251 Spring 2023
// Engineer: Lizelle Ocfemia & Nicholas Storniolo
// 
//     Create Date: 2023-05-01
//     Module Name: clock
//     Description: Clock generator; duty cycle = 50%
//
// Revision: 1.0
//
//////////////////////////////////////////////////////////////////////////////////
`ifndef CLOCK
`define CLOCK

`timescale 1ns/100ps

module clock
    #(parameter ticks = 10)(
    //
    // ---------------- PORT DEFINITIONS ----------------
    //
    input ENABLE,
    output reg CLOCK
);
    //
    // ---------------- MODULE DESIGN IMPLEMENTATION ----------------
    //
    reg start_clock;
    real clock_on = ticks/2; // duty cycle = 50%
    real clock_off = ticks/2;

    // initialize variables
    initial begin
      CLOCK <= 0;
      start_clock <= 0;
    end

    always @(posedge ENABLE or negedge ENABLE) begin
        if (ENABLE) begin
            start_clock = 1;
        end
        else begin
            start_clock = 0;
        end
        // #ticks CLOCK = ~CLOCK;
    end
    always @(start_clock) begin
        CLOCK = 0;
        while (start_clock) begin
            #(clock_off) CLOCK = 1;
            #(clock_on) CLOCK = 0;
        end
        CLOCK = 0;
    end
endmodule

`endif // CLOCK

gigaHurt/components/aludec/aludec.sv
//////////////////////////////////////////////////////////////////////////////////
// The Cooper Union
// ECE 251 Spring 2023
// Engineer: gigaHurt
// 
//     Create Date: 2023-02-07
//     Module Name: aludec
//     Description: 16-bit RISC-based ALU decoder (MIPS)
//
// Revision: 1.0
//
//////////////////////////////////////////////////////////////////////////////////
`ifndef ALUDEC
`define ALUDEC

module aludec(
    //
    // ---------------- PORT DEFINITIONS ----------------
    //
    input logic [3:0] funct,
    input logic [1:0] aluop,
    output logic [3:0] alucontrol
);
    //
    // ---------------- MODULE DESIGN IMPLEMENTATION ----------------
    //
    always @*
    case(aluop) // all this does is make funct = alucontrol
        2'b00: alucontrol <= 4'b0011; // add (for lw/sw/addi)
        2'b01: alucontrol <= 4'b0100; // sub (for beq)
        default:
            case(funct) // R-type instructions
                4'b0000: alucontrol <= 4'b0000; // and
                4'b0001: alucontrol <= 4'b0001; // or
                4'b0010: alucontrol <= 4'b0010; // nor
                4'b0011: alucontrol <= 4'b0011; // add
                4'b0100: alucontrol <= 4'b0100; // sub
                4'b0101: alucontrol <= 4'b0101; // mul
                4'b1000: alucontrol <= 4'b1000; // div
                4'b1001: alucontrol <= 4'b1001; // slt
                4'b1010: alucontrol <= 4'b1010; // jr

                default: alucontrol <= 4'bxxxx; // ???
            endcase
    endcase

endmodule

`endif // ALUDEC

gigaHurt/components/aludec/aludec_tb.sv
//////////////////////////////////////////////////////////////////////////////////
// The Cooper Union
// ECE 251 Spring 2023
// Engineer: gigaHurt
// 
//     Create Date: 2023-02-07
//     Module Name: maindec_tb
//     Description: Controls signal decoder testbench
//
// Revision: 1.0
//
//////////////////////////////////////////////////////////////////////////////////
`ifndef TB_MAINDEC
`define TB_MAINDEC

`timescale 1ns/100ps
`include "aludec.sv"
`include "../clock/clock.sv"

module aludec_tb;
    logic [3:0] funct;
    logic [1:0] aluop;
    logic [3:0] alucontrol;
    integer i;

   initial begin
        $dumpfile("aludec.vcd");
        $dumpvars(0, uut);
        $monitor("time=%0t funct=%b aluop=%b alucontrol=%b",
            $realtime, funct, aluop, alucontrol);
    end

    initial begin
        #10 funct <= 4'b0;
        for (i=0; i<10; i = i+1)
        begin
            funct = funct + 3'b001;
            #10;
        end
        $finish;
    end
    
   aludec uut(
        .funct(funct),
        .aluop(aluop),
        .alucontrol(alucontrol)
    );

endmodule

`endif // maindec

gigaHurt/components/aludec/aludec.vcd
$date
	Fri May 12 19:47:46 2023
$end
$version
	Icarus Verilog
$end
$timescale
	100ps
$end
$scope module aludec_tb $end
$scope module uut $end
$var wire 2 ! aluop [1:0] $end
$var wire 4 " funct [3:0] $end
$var reg 4 # alucontrol [3:0] $end
$upscope $end
$upscope $end
$enddefinitions $end
#0
$dumpvars
bx #
bx "
bx !
$end
#100
b0 #
b0 "
#200
b100 #
b1 "
#300
b0 #
b10 "
#400
b1 #
b11 "
#500
b111 #
b100 "
#600
b101 #
b101 "
#700
bx #
b110 "
#800
b111 "
#900
b1000 #
b1000 "
#1000
b1001 #
b1001 "
