gigaHurt/components/clock/clock.sv
//////////////////////////////////////////////////////////////////////////////////
// The Cooper Union
// ECE 251 Spring 2023
// Engineer: Lizelle Ocfemia & Nicholas Storniolo
// 
//     Create Date: 2023-05-01
//     Module Name: clock
//     Description: Clock generator; duty cycle = 50%
//
// Revision: 1.0
//
//////////////////////////////////////////////////////////////////////////////////
`ifndef CLOCK
`define CLOCK

`timescale 1ns/100ps

module clock
    #(parameter ticks = 10)(
    //
    // ---------------- PORT DEFINITIONS ----------------
    //
    input ENABLE,
    output reg CLOCK
);
    //
    // ---------------- MODULE DESIGN IMPLEMENTATION ----------------
    //
    reg start_clock;
    real clock_on = ticks/2; // duty cycle = 50%
    real clock_off = ticks/2;

    // initialize variables
    initial begin
      CLOCK <= 0;
      start_clock <= 0;
    end

    always @(posedge ENABLE or negedge ENABLE) begin
        if (ENABLE) begin
            start_clock = 1;
        end
        else begin
            start_clock = 0;
        end
        // #ticks CLOCK = ~CLOCK;
    end
    always @(start_clock) begin
        CLOCK = 0;
        while (start_clock) begin
            #(clock_off) CLOCK = 1;
            #(clock_on) CLOCK = 0;
        end
        CLOCK = 0;
    end
endmodule

`endif // CLOCK

gigaHurt/components/maindec/maindec.sv
//////////////////////////////////////////////////////////////////////////////////
// The Cooper Union
// ECE 251 Spring 2023
// Engineer: gigaHurt
// 
//     Create Date: 2023-02-07
//     Module Name: maindec
//     Description: 16-bit RISC-based CPU main decoder (MIPS)
//
// Revision: 1.0
//
//////////////////////////////////////////////////////////////////////////////////
`ifndef MAINDEC
`define MAINDEC

`timescale 1ns/100ps

module maindec
    #(parameter n = 16)(
    //
    // ---------------- PORT DEFINITIONS ----------------
    //
    input  logic [2:0] op,
    output logic       memtoreg, memwrite,
    output logic       branch, alusrc,
    output logic       regdst, regwrite,
    output logic       jump,
    output logic [1:0] aluop
);
    //
    // ---------------- MODULE DESIGN IMPLEMENTATION ----------------
    //
    logic [8:0] controls; // 9-bit control vector

    // controls has 9 logical signals
    assign {memtoreg, memwrite, alusrc, branch,
            regdst, regwrite, jump, aluop} = controls;

    always @* begin
        case(op)
            3'b000: controls <= 9'b000011010; // RTYPE
            
            3'b001: controls <= 9'b011001000; // LW
            3'b010: controls <= 9'b011000000; // SW
            3'b011: controls <= 9'b001001000; // ADDI
            3'b100: controls <= 9'b001001000; // SUBI -> should change to BGT?
            3'b101: controls <= 9'b000000100; // BEQ

            3'b110: controls <= 9'b000000100; // J
            3'b111: controls <= 9'b000000100; // JAL
            default:   controls <= 9'bxxxxxxxxx; // illegal operation
        endcase
    end

endmodule

`endif // MAINDEC

gigaHurt/components/maindec/maindec_tb.sv
//////////////////////////////////////////////////////////////////////////////////
// The Cooper Union
// ECE 251 Spring 2023
// Engineer: gigaHurt
// 
//     Create Date: 2023-02-07
//     Module Name: maindec_tb
//     Description: Controls signal decoder testbench
//
// Revision: 1.0
//
//////////////////////////////////////////////////////////////////////////////////
`ifndef TB_MAINDEC
`define TB_MAINDEC

`timescale 1ns/100ps
`include "maindec.sv"
`include "../clock/clock.sv"

module maindec_tb;
    logic [2:0] op;
    logic memtoreg, memwrite, branch;
    logic alusrc, regdst, regwrite, jump;
    logic [1:0] aluop;
    integer i;

   initial begin
        $dumpfile("maindec.vcd");
        $dumpvars(0, uut);
        $monitor("time=%0t op=%b memtoreg=%b memwrite=%b alusrc=%b branch=%b regdst=%b regwrite=%b jump=%b aluop=%b",
            $realtime, op, memtoreg, memwrite, alusrc, branch, regdst, regwrite, jump, aluop);
    end

    initial begin
        #10 op <= 3'b0;

        for (i=0; i<8; i = i+1)
        begin
            op = op + 3'b001;
            #10;
        end
        $finish;
    end
    
   maindec uut(
        .op(op),
        .memtoreg(memtoreg),
        .memwrite(memwrite),
        .branch(branch),
        .alusrc(alusrc),
        .regdst(regdst),
        .regwrite(regwrite),
        .jump(jump),
        .aluop(aluop)
    );

endmodule

`endif // maindec

gigaHurt/components/maindec/maindec.vcd
$date
	Fri May 12 20:12:22 2023
$end
$version
	Icarus Verilog
$end
$timescale
	100ps
$end
$scope module maindec_tb $end
$scope module uut $end
$var wire 3 ! op [2:0] $end
$var wire 1 " regwrite $end
$var wire 1 # regdst $end
$var wire 1 $ memwrite $end
$var wire 1 % memtoreg $end
$var wire 1 & jump $end
$var wire 1 ' branch $end
$var wire 1 ( alusrc $end
$var wire 2 ) aluop [1:0] $end
$var reg 9 * controls [8:0] $end
$upscope $end
$upscope $end
$enddefinitions $end
#0
$dumpvars
bx *
bx )
x(
x'
x&
x%
x$
x#
x"
bx !
$end
#100
0%
0$
0(
0'
1#
1"
0&
b10 )
b11010 *
b0 !
#200
1$
1(
0#
b0 )
b11001000 *
b1 !
#300
0"
b11000000 *
b10 !
#400
0$
1"
b1001000 *
b11 !
#500
x%
x$
x(
x'
x#
x"
x&
bx )
bx *
b100 !
#600
0%
0$
0(
1'
0#
0"
0&
b1 )
b100001 *
b101 !
#700
0'
1&
b0 )
b100 *
b110 !
#800
b111 !
