gigaHurt/components/clock/clock.sv
//////////////////////////////////////////////////////////////////////////////////
// The Cooper Union
// ECE 251 Spring 2023
// Engineer: Lizelle Ocfemia & Nicholas Storniolo
// 
//     Create Date: 2023-05-01
//     Module Name: clock
//     Description: Clock generator; duty cycle = 50%
//
// Revision: 1.0
//
//////////////////////////////////////////////////////////////////////////////////
`ifndef CLOCK
`define CLOCK

`timescale 1ns/100ps

module clock
    #(parameter ticks = 10)(
    //
    // ---------------- PORT DEFINITIONS ----------------
    //
    input ENABLE,
    output reg CLOCK
);
    //
    // ---------------- MODULE DESIGN IMPLEMENTATION ----------------
    //
    reg start_clock;
    real clock_on = ticks/2; // duty cycle = 50%
    real clock_off = ticks/2;

    // initialize variables
    initial begin
      CLOCK <= 0;
      start_clock <= 0;
    end

    always @(posedge ENABLE or negedge ENABLE) begin
        if (ENABLE) begin
            start_clock = 1;
        end
        else begin
            start_clock = 0;
        end
        // #ticks CLOCK = ~CLOCK;
    end
    always @(start_clock) begin
        CLOCK = 0;
        while (start_clock) begin
            #(clock_off) CLOCK = 1;
            #(clock_on) CLOCK = 0;
        end
        CLOCK = 0;
    end
endmodule

`endif // CLOCK

gigaHurt/components/dff/dff.sv
//////////////////////////////////////////////////////////////////////////////////
// The Cooper Union
// ECE 251 Spring 2023
// Engineer: Lizelle Ocfemia & Nicholas Storniolo
// 
//     Create Date: 2023-05-01
//     Module Name: dff
//     Description: 16 bit D flip flop
//
// Revision: 1.0
//
//////////////////////////////////////////////////////////////////////////////////
`ifndef DFF
`define DFF

`timescale 1ns/100ps

module dff
    #(parameter n = 16)(
    //
    // ---------------- PORT DEFINITIONS ----------------
    //
    input  logic CLOCK, RESET,
    input  logic [(n-1):0] D,
    output logic [(n-1):0] Q
);
    //
    // ---------------- MODULE DESIGN IMPLEMENTATION ----------------
    //
    always @(posedge CLOCK, posedge RESET)
    begin
        if (RESET)
        begin
            Q <= 0;
        end
        else
        begin
            Q <= D;
        end
    end
endmodule

`endif // DFF

gigaHurt/components/dff/dff_tb.sv
//////////////////////////////////////////////////////////////////////////////////
// The Cooper Union
// ECE 251 Spring 2023
// Engineer: Prof Rob Marano
// 
//     Create Date: 2023-02-07
//     Module Name: tb_dff
//     Description: Test bench for 32 bit D flip flop
//
// Revision: 1.0
//
//////////////////////////////////////////////////////////////////////////////////
`ifndef TB_DFF
`define TB_DFF

`timescale 1ns/100ps
`include "dff.sv"
`include "../clock/clock.sv"

module tb_dff;
    parameter n = 16; // #bits for an operand
    wire clk;
    logic enable;
    logic reset;
    logic [(n-1):0] d;
    logic [(n-1):0] q;

   initial begin
        $dumpfile("dff.vcd");
        $dumpvars(0, uut0, uut1);
        //$monitor("d = %b (0x%0h)(%0d) q = %b (0x%0h)(%0d) ", d,d,d,q,q,q);
        $monitor("time=%0t \t d=%h q=%h",$realtime, d, q);
    end

    initial begin
        d <= #n'h8000;
        enable <= 0;
        #10 enable <= 1;
        #10 reset <= 1;
        #20 d <= #n'h0001;
        #10 reset <= 0;
        #10 reset <=0;
        #20 d <= #n'h0001;
        #100 enable <= 0;
        $finish;        
    end

    dff uut0(
        .CLOCK(clk), .RESET(reset), .D(d), .Q(q)
    );

   clock uut1(
        .ENABLE(enable),
        .CLOCK(clk)
    );
endmodule
`endif // TB_DFF

gigaHurt/components/dff/dff.vcd
$date
	Mon May  1 16:25:01 2023
$end
$version
	Icarus Verilog
$end
$timescale
	100ps
$end
$scope module tb_dff $end
$scope module uut0 $end
$var wire 16 ! D [15:0] $end
$var wire 1 " RESET $end
$var wire 1 # CLOCK $end
$var reg 16 $ Q [15:0] $end
$upscope $end
$upscope $end
$scope module tb_dff $end
$scope module uut1 $end
$var wire 1 % ENABLE $end
$var reg 1 # CLOCK $end
$var reg 1 & start_clock $end
$var real 1 ' clock_off $end
$var real 1 ( clock_on $end
$upscope $end
$upscope $end
$enddefinitions $end
#0
$dumpvars
r5 (
r5 '
0&
0%
bx $
0#
x"
bx !
$end
#100
1&
1%
#150
1#
#160
b1000000000000000 !
#200
b0 $
1"
0#
#250
1#
#300
0#
#350
1#
#400
0#
#450
1#
#500
0"
0#
#550
b1000000000000000 $
1#
#560
b1 !
#600
0#
#650
b1 $
1#
#700
0#
#750
1#
#800
0#
#850
1#
#900
0#
#950
1#
#1000
0#
#1050
1#
#1100
0#
#1150
1#
#1200
0#
#1250
1#
#1300
0#
#1350
1#
#1400
0#
#1450
1#
#1500
0#
#1550
1#
#1600
0#
#1650
1#
#1700
0#
#1750
1#
#1800
0&
0%
0#
